orangecontrib/__init__.py
orangecontrib/custom/__init__.py
orangecontrib/custom/widgets/__init__.py
orangecontrib/custom/widgets/hstack.py
orangecontrib/custom/widgets/pdf_converter PYQT based.py
orangecontrib/custom/widgets/pdf_converter.py
orangecontrib/custom/widgets/regex.py
orangecontrib/custom/widgets/icons/category.png
orangecontrib/custom/widgets/icons/hstack.svg
orangecontrib/custom/widgets/icons/pdf_converter.svg
orangecontrib/custom/widgets/icons/regex.svg
orangecontrib/custom/widgets/web_UI/__pycache__/__init__.cpython-311.pyc
orangecontrib/custom/widgets/web_UI/__pycache__/camelot.cpython-310.pyc
orangecontrib/custom/widgets/web_UI/__pycache__/main.cpython-311.pyc
orangecontrib/custom/widgets/web_UI/pdf_converter_gui/copy-link-icon.webp
orangecontrib/custom/widgets/web_UI/pdf_converter_gui/file-pdf.svg
orangecontrib/custom/widgets/web_UI/pdf_converter_gui/index.html
orangecontrib/custom/widgets/web_UI/pdf_converter_gui/page_1.png
orangecontrib/custom/widgets/web_UI/pdf_converter_gui/qwebchannel.js
orangecontrib/custom/widgets/web_UI/pdf_converter_gui/restoreHtml.js
orangecontrib/custom/widgets/web_UI/pdf_converter_gui/semantic_ui.css
orangecontrib/custom/widgets/web_UI/pdf_converter_gui/style.css
orangecontrib/custom/widgets/web_UI/pdf_converter_gui/rulerguides/README.md
orangecontrib/custom/widgets/web_UI/pdf_converter_gui/rulerguides/RulersGuides.js
orangecontrib/custom/widgets/web_UI/pdf_converter_gui/rulerguides/bookmarklet.js
orangecontrib/custom/widgets/web_UI/pdf_converter_gui/rulerguides/bookmarklet_ie.js
orangecontrib/custom/widgets/web_UI/pdf_converter_gui/rulerguides/mit-license.txt
orangecontrib/custom/widgets/web_UI/pdf_converter_gui/rulerguides/rulersguides.css
orangecontrib/custom/widgets/web_UI/pdf_converter_gui/rulerguides/demo/index.css
orangecontrib/custom/widgets/web_UI/pdf_converter_gui/rulerguides/demo/index.html
orangecontrib/custom/widgets/web_UI/regex_ui/index.html
orangecontrib/custom/widgets/web_UI/regex_ui/qwebchannel.js
orange3_datasieve-0.1.5.dist-info/METADATA
orange3_datasieve-0.1.5.dist-info/WHEEL
orange3_datasieve-0.1.5.dist-info/entry_points.txt
orange3_datasieve-0.1.5.dist-info/top_level.txt
orange3_datasieve-0.1.5.dist-info/RECORD
