Metadata-Version: 2.4
Name: Orange3-DataSieve
Version: 0.1.5
Summary: This add-on includes a suite of widgets designed to extract and parse data from PDFs. It also offers advanced data cleaning features, including regex-based processing, string manipulation, and more. For collaboration or inquiries, contact Mehdi Benrabiaa at Todds496@gmail.com
Home-page: 
Author: EL_MEHDI_BEN_RABIAA
Author-email: todds496@gmail.com
License: BSD
Keywords: orange3 add-on
Requires-Dist: pypdfium2==5.0.0
Requires-Dist: PyQtWebEngine==5.15.7
Requires-Dist: camelot-py==1.0.9
Requires-Dist: numpy==1.25.0
Dynamic: author
Dynamic: author-email
Dynamic: description
Dynamic: description-content-type
Dynamic: keywords
Dynamic: license
Dynamic: requires-dist
Dynamic: summary
